nakplae/__init__.py
nakplae/__main__.py
nakplae/transcribe.py
nakplae/translate.py
nakplae-1.1.4.dist-info/LICENSE
nakplae-1.1.4.dist-info/METADATA
nakplae-1.1.4.dist-info/WHEEL
nakplae-1.1.4.dist-info/entry_points.txt
nakplae-1.1.4.dist-info/top_level.txt
nakplae-1.1.4.dist-info/RECORD
