Metadata-Version: 2.2
Name: nakplae
Version: 1.1.4
Summary: Video transcription and translation tool using Whisper and Gemini
Author-email: Eli Mydlarz <eli@mydlarz.com>
License: MIT
Project-URL: Homepage, https://github.com/elimydlarz/nakplae
Project-URL: Bug Tracker, https://github.com/elimydlarz/nakplae/issues
Project-URL: Documentation, https://github.com/elimydlarz/nakplae#readme
Project-URL: Source Code, https://github.com/elimydlarz/nakplae
Keywords: whisper,transcription,translation,subtitles,srt,gemini,video
Classifier: Development Status :: 5 - Production/Stable
Classifier: Intended Audience :: End Users/Desktop
Classifier: Programming Language :: Python :: 3
Classifier: Programming Language :: Python :: 3.10
Classifier: Programming Language :: Python :: 3.11
Classifier: Programming Language :: Python :: 3.12
Classifier: License :: OSI Approved :: MIT License
Classifier: Operating System :: OS Independent
Classifier: Topic :: Multimedia :: Video
Classifier: Topic :: Text Processing :: Linguistic
Requires-Python: >=3.10
License-File: LICENSE
Requires-Dist: openai-whisper>=20230918
Requires-Dist: google-generativeai>=0.3.0
Requires-Dist: gemini-srt-translator>=1.3.0
Requires-Dist: tqdm>=4.65.0
Requires-Dist: torch>=2.0.0
Provides-Extra: dev
Requires-Dist: pytest>=7.0.0; extra == "dev"
Requires-Dist: black>=23.0.0; extra == "dev"
Requires-Dist: ruff>=0.0.240; extra == "dev"
Requires-Dist: mypy>=1.0.0; extra == "dev"
Requires-Dist: build; extra == "dev"
Requires-Dist: twine; extra == "dev"
